multiset_key_dict/__init__.py
multiset_key_dict/frozen_multiset.py
multiset_key_dict/multiset_key_dict.py
multiset_key_dict-0.2.1.dist-info/licenses/LICENSE
multiset_key_dict-0.2.1.dist-info/METADATA
multiset_key_dict-0.2.1.dist-info/WHEEL
multiset_key_dict-0.2.1.dist-info/top_level.txt
multiset_key_dict-0.2.1.dist-info/RECORD
