Metadata-Version: 2.4
Name: multiset-key-dict
Version: 0.2.1
Summary: A simple library for executing BLAST searches with ncbi-blast+
Author-email: Andrew Tapia <andrew.tapia@uky.edu>
Project-URL: Homepage, https://github.com/actapia/multiset-key-dict
Project-URL: Bug Tracker, https://github.com/actapia/multiset-key-dict
Classifier: Programming Language :: Python :: 3
Classifier: License :: OSI Approved :: MIT License
Classifier: Operating System :: OS Independent
Requires-Python: >=3.12
License-File: LICENSE
Dynamic: license-file
